Metadata-Version: 1.1
Name: gtfs-realtime-bindings
Version: 0.0.1
Summary: Python classes generated from the GTFS-realtime protocol buffer specification.
Home-page: https://github.com/google/gtfs-realtime-bindings
Author: Google Inc.
Author-email: gtfs-realtime@googlegroups.com
License: Apache License, Version 2.0
Platform: UNKNOWN
Classifier: Intended Audience :: Developers
Classifier: License :: OSI Approved :: Apache Software License
Classifier: Operating System :: OS Independent
Classifier: Programming Language :: Python
Classifier: Topic :: Software Development :: Libraries :: Python Modules
